gpkg.hello-0.6.0-py2.7-nspkg.pth
gpkg/hello/guild.yml
gpkg/hello/msg.txt
gpkg/hello/say.py
gpkg.hello-0.6.0.dist-info/METADATA
gpkg.hello-0.6.0.dist-info/PACKAGE
gpkg.hello-0.6.0.dist-info/WHEEL
gpkg.hello-0.6.0.dist-info/entry_points.txt
gpkg.hello-0.6.0.dist-info/namespace_packages.txt
gpkg.hello-0.6.0.dist-info/top_level.txt
gpkg.hello-0.6.0.dist-info/RECORD
