Metadata-Version: 2.1
Name: gpkg.hello
Version: 0.6.0
Summary: Sample "hello world" model (Guild AI)
Home-page: https://github.com/guildai/packages/tree/master/gpkg/hello
Author: Guild AI
Author-email: packages@guild.ai
License: Apache 2.0
Keywords: gpkg
Platform: UNKNOWN
